{
  "pSubareaManager": {
    "vSubareaSetups": [
      {
        "sId": "Default",
        "vSubareaConfigs": [
          {
            "sId": "GLOBAL",
            "sSetupId": "Default",
            "bDisableSubArea": 0,
            "fCameraZDistance": -1.0,
            "bIgnoreMetroidCameraOffsets": 0,
            "sCharclassGroupId": "",
            "asItemsIds": [
              "",
              "lg_GLOBAL_Default",
              "ssg_GLOBAL_Default",
              "sg_SubArea_GLOBAL",
              "eg_GLOBAL_Default",
              "bg_SubArea_GLOBAL",
              "default",
              "",
              ""
            ],
            "vsCameraCollisionsIds": [],
            "vsCutscenesIds": []
          },
          {
            "sId": "collision_camera_000",
            "sSetupId": "Default",
            "bDisableSubArea": 0,
            "fCameraZDistance": -1.0,
            "bIgnoreMetroidCameraOffsets": 0,
            "sCharclassGroupId": "Commander",
            "asItemsIds": [
              "",
              "lg_collision_camera_000_Default",
              "ssg_collision_camera_000_Default",
              "sg_SubArea_collision_camera_000",
              "eg_collision_camera_000_Default",
              "bg_SubArea_collision_camera_000",
              "Savestation_R",
              "",
              "savestation"
            ],
            "vsCameraCollisionsIds": [
              "collision_camera_000"
            ],
            "vsCutscenesIds": []
          },
          {
            "sId": "collision_camera_001",
            "sSetupId": "Default",
            "bDisableSubArea": 0,
            "fCameraZDistance": -1.0,
            "bIgnoreMetroidCameraOffsets": 0,
            "sCharclassGroupId": "Commander",
            "asItemsIds": [
              "",
              "lg_collision_camera_001_Default",
              "ssg_collision_camera_001_Default",
              "sg_SubArea_collision_camera_001",
              "eg_collision_camera_001_Default",
              "bg_SubArea_collision_camera_001",
              "Skybase",
              "",
              "s_skybase_001"
            ],
            "vsCameraCollisionsIds": [
              "collision_camera_001"
            ],
            "vsCutscenesIds": []
          },
          {
            "sId": "collision_camera_002",
            "sSetupId": "Default",
            "bDisableSubArea": 0,
            "fCameraZDistance": 4080.0,
            "bIgnoreMetroidCameraOffsets": 0,
            "sCharclassGroupId": "Commander",
            "asItemsIds": [
              "",
              "lg_collision_camera_002_Default",
              "ssg_collision_camera_002_Default",
              "sg_SubArea_collision_camera_002",
              "eg_collision_camera_002_Default",
              "bg_SubArea_collision_camera_002",
              "Skybase_2",
              "",
              "s_skybase_001"
            ],
            "vsCameraCollisionsIds": [
              "collision_camera_002"
            ],
            "vsCutscenesIds": []
          },
          {
            "sId": "collision_camera_003",
            "sSetupId": "Default",
            "bDisableSubArea": 0,
            "fCameraZDistance": -1.0,
            "bIgnoreMetroidCameraOffsets": 0,
            "sCharclassGroupId": "Commander",
            "asItemsIds": [
              "",
              "lg_collision_camera_003_Default",
              "ssg_collision_camera_003_Default",
              "sg_SubArea_collision_camera_003",
              "eg_collision_camera_003_Default",
              "bg_SubArea_collision_camera_003",
              "default",
              "",
              "no_music"
            ],
            "vsCameraCollisionsIds": [
              "collision_camera_003"
            ],
            "vsCutscenesIds": []
          },
          {
            "sId": "collision_camera_004",
            "sSetupId": "Default",
            "bDisableSubArea": 0,
            "fCameraZDistance": -1.0,
            "bIgnoreMetroidCameraOffsets": 0,
            "sCharclassGroupId": "Commander",
            "asItemsIds": [
              "",
              "lg_collision_camera_004_Default",
              "ssg_collision_camera_004_Default",
              "sg_SubArea_collision_camera_004",
              "eg_collision_camera_004_Default",
              "bg_SubArea_collision_camera_004",
              "Final_Boss_black_v3",
              "",
              "no_music"
            ],
            "vsCameraCollisionsIds": [
              "collision_camera_004"
            ],
            "vsCutscenesIds": []
          },
          {
            "sId": "collision_camera_005",
            "sSetupId": "Default",
            "bDisableSubArea": 0,
            "fCameraZDistance": 0.0,
            "bIgnoreMetroidCameraOffsets": 0,
            "sCharclassGroupId": "Commander",
            "asItemsIds": [
              "",
              "lg_collision_camera_005_Default",
              "ssg_collision_camera_005_Default",
              "sg_SubArea_collision_camera_005",
              "eg_collision_camera_005_Default",
              "bg_SubArea_collision_camera_005",
              "Comunication_room_005",
              "",
              "accesspoint"
            ],
            "vsCameraCollisionsIds": [
              "collision_camera_005"
            ],
            "vsCutscenesIds": []
          },
          {
            "sId": "collision_camera_SHIPYARD",
            "sSetupId": "Default",
            "bDisableSubArea": 0,
            "fCameraZDistance": 0.0,
            "bIgnoreMetroidCameraOffsets": 0,
            "sCharclassGroupId": "Commander",
            "asItemsIds": [
              "",
              "lg_collision_camera_SHIPYARD_Default",
              "ssg_collision_camera_SHIPYARD_Default",
              "sg_SubArea_collision_camera_900",
              "eg_collision_camera_SHIPYARD_Default",
              "bg_SubArea_collision_camera_SHIPYARD",
              "Final_Boss_black_v3_Fog_version",
              "",
              "no_music"
            ],
            "vsCameraCollisionsIds": [
              "collision_camera_900"
            ],
            "vsCutscenesIds": []
          }
        ]
      },
      {
        "sId": "ChangeCamera_002_Distance",
        "vSubareaConfigs": [
          {
            "sId": "collision_camera_002",
            "sSetupId": "ChangeCamera_002_Distance",
            "bDisableSubArea": 0,
            "fCameraZDistance": 2630.0,
            "bIgnoreMetroidCameraOffsets": 0,
            "sCharclassGroupId": "Commander",
            "asItemsIds": [
              "",
              "",
              "ssg_collision_camera_002_ChangeCamera_002_Distance",
              "",
              "",
              "",
              "",
              "",
              ""
            ],
            "vsCameraCollisionsIds": [
              "collision_camera_002"
            ],
            "vsCutscenesIds": []
          }
        ]
      }
    ],
    "vCharclassGroups": [
      {
        "sId": "No Enemies",
        "vsCharClassesIds": []
      },
      {
        "sId": "Commander",
        "vsCharClassesIds": [
          "chozocommander"
        ]
      }
    ]
  }
}