{
  "FileType": "CCutSceneDef",
  "Unk": 33751048,
  "RealFileType": "CCutSceneDef",
  "Root": {
    "eDevelopmentState": "WorkInProgress",
    "sId": "0035protoemmycantclimb",
    "sActionSet": "cutscenes/0035protoemmycantclimb/0035protoemmycantclimb.bmsas",
    "vWorldOffset": [
      21078.80078125,
      -2434.199951171875,
      -3.5
    ],
    "sOnLoaded": "",
    "sOnBeforeStart": "",
    "sOnStart": "s010_cave.OnProtoEmmyCantClimbCutsceneStart",
    "sOnFinished": "",
    "sOnEnd": "s010_cave.OnProtoEmmyCantClimbCutsceneEnd",
    "sOnSkip": "",
    "fCamInitInterpTime": -1.0,
    "fCamExitInterpTime": 0.10000000149011612,
    "fFps": 30,
    "bSkippable": true,
    "aTakes": [
      {
        "sId": "1",
        "iFrames": 275,
        "sCamera": "cutscenes/0035protoemmycantclimb/cameras/1.bccam",
        "sOnStart": "",
        "sOnExit": "",
        "sOnSkip": "",
        "fInitialDistanceListenerToTarget": 0.0,
        "fMinimumDistanceListenerToTarget": -1.0,
        "fMaximumDistanceListenerToTarget": -1.0
      }
    ],
    "aActors": [
      {
        "sId": "0035protoemmycantclimb_samus",
        "sCharClass": "actors/cutscene/samus.bmsad",
        "sInGameEntityId": "",
        "bInGameEntityVisibleOnEnd": true,
        "bExitClearTags": false,
        "fExitAnimTags": 0,
        "dBlendSpaceVars": {},
        "sSkelRootNode": "",
        "sExitAnim": "relaxshot",
        "sExitAnimChannel": "default",
        "fExitAnimFrame": 0.0,
        "dLayersExitAnim": {},
        "sLightingDef": ""
      },
      {
        "sId": "0035protoemmycantclimb_emmy",
        "sCharClass": "actors/cutscene/emmy_proto.bmsad",
        "sInGameEntityId": "SP_EmmyProto",
        "bInGameEntityVisibleOnEnd": true,
        "bExitClearTags": false,
        "fExitAnimTags": 0,
        "dBlendSpaceVars": {},
        "sSkelRootNode": "",
        "sExitAnim": "ncu_chasenear-scratch_loop-wall",
        "sExitAnimChannel": "default",
        "fExitAnimFrame": 0.0,
        "dLayersExitAnim": {},
        "sLightingDef": ""
      },
      {
        "sId": "0035protoemmycantclimb_cutmodel49wall01subchar",
        "sCharClass": "cutscenes/0035protoemmycantclimb/actors/cutmodel49wall01subchar/actor.bmsad",
        "sInGameEntityId": "",
        "bInGameEntityVisibleOnEnd": true,
        "bExitClearTags": false,
        "fExitAnimTags": 0,
        "dBlendSpaceVars": {},
        "sSkelRootNode": "",
        "sExitAnim": "",
        "sExitAnimChannel": "default",
        "fExitAnimFrame": 0.0,
        "dLayersExitAnim": {},
        "sLightingDef": ""
      }
    ],
    "aSounds": [],
    "oPoolDefinitions": {
      "lPoolDefinitions": [
        {
          "sFile": "cutscenes/0035protoemmycantclimb/fx/protoemmy_arm.bcptl",
          "eType": "FXTYPE_PARTICLESYSTEM",
          "uSize": 1
        },
        {
          "sFile": "cutscenes/0035protoemmycantclimb/fx/protoemmy_body.bcptl",
          "eType": "FXTYPE_PARTICLESYSTEM",
          "uSize": 1
        },
        {
          "sFile": "cutscenes/0035protoemmycantclimb/fx/impact_arm.bcptl",
          "eType": "FXTYPE_PARTICLESYSTEM",
          "uSize": 3
        },
        {
          "sFile": "cutscenes/0035protoemmycantclimb/fx/electro_blue.bcptl",
          "eType": "FXTYPE_PARTICLESYSTEM",
          "uSize": 4
        },
        {
          "sFile": "cutscenes/0035protoemmycantclimb/fx/sparks_loop.bcptl",
          "eType": "FXTYPE_PARTICLESYSTEM",
          "uSize": 2
        },
        {
          "sFile": "cutscenes/0035protoemmycantclimb/fx/sparks_04.bcptl",
          "eType": "FXTYPE_PARTICLESYSTEM",
          "uSize": 1
        }
      ]
    }
  }
}